[
    {
        "name": "Anitta",
        "category": "auto"
    },
    {
        "name": "Ludmilla",
        "category": "auto"
    },
    {
        "name": "Pabllo Vittar",
        "category": "auto"
    },
    {
        "name": "Gloria Groove",
        "category": "auto"
    },
    {
        "name": "Luísa Sonza",
        "category": "auto"
    },
    {
        "name": "Iza",
        "category": "auto"
    },
    {
        "name": "Lexa",
        "category": "auto"
    },
    {
        "name": "MC Mirella",
        "category": "auto"
    },
    {
        "name": "MC Poze do Rodo",
        "category": "auto"
    },
    {
        "name": "MC Livinho",
        "category": "auto"
    },
    {
        "name": "Kevinho",
        "category": "auto"
    },
    {
        "name": "MC Guimê",
        "category": "auto"
    },
    {
        "name": "MC Lan",
        "category": "auto"
    },
    {
        "name": "MC Hariel",
        "category": "auto"
    },
    {
        "name": "MC Ryan SP",
        "category": "auto"
    },
    {
        "name": "MC Cabelinho",
        "category": "auto"
    },
    {
        "name": "MC Pedrinho",
        "category": "auto"
    },
    {
        "name": "MC Pipokinha",
        "category": "auto"
    },
    {
        "name": "Matuê",
        "category": "auto"
    },
    {
        "name": "Teto",
        "category": "auto"
    },
    {
        "name": "Veigh",
        "category": "auto"
    },
    {
        "name": "L7NNON",
        "category": "auto"
    },
    {
        "name": "Djonga",
        "category": "auto"
    },
    {
        "name": "Filipe Ret",
        "category": "auto"
    },
    {
        "name": "Xamã",
        "category": "auto"
    },
    {
        "name": "Emicida",
        "category": "auto"
    },
    {
        "name": "Criolo",
        "category": "auto"
    },
    {
        "name": "Karol Conká",
        "category": "auto"
    },
    {
        "name": "Rashid",
        "category": "auto"
    },
    {
        "name": "Mano Brown",
        "category": "auto"
    },
    {
        "name": "Caetano Veloso",
        "category": "auto"
    },
    {
        "name": "Gilberto Gil",
        "category": "auto"
    },
    {
        "name": "Chico Buarque",
        "category": "auto"
    },
    {
        "name": "Maria Bethânia",
        "category": "auto"
    },
    {
        "name": "Djavan",
        "category": "auto"
    },
    {
        "name": "Milton Nascimento",
        "category": "auto"
    },
    {
        "name": "Jorge Ben Jor",
        "category": "auto"
    },
    {
        "name": "Zeca Pagodinho",
        "category": "auto"
    },
    {
        "name": "Martinho da Vila",
        "category": "auto"
    },
    {
        "name": "Arlindo Cruz",
        "category": "auto"
    },
    {
        "name": "Beth Carvalho",
        "category": "auto"
    },
    {
        "name": "Alcione",
        "category": "auto"
    },
    {
        "name": "Ivete Sangalo",
        "category": "auto"
    },
    {
        "name": "Claudia Leitte",
        "category": "auto"
    },
    {
        "name": "Daniela Mercury",
        "category": "auto"
    },
    {
        "name": "Bell Marques",
        "category": "auto"
    },
    {
        "name": "Saulo Fernandes",
        "category": "auto"
    },
    {
        "name": "Léo Santana",
        "category": "auto"
    },
    {
        "name": "Thiaguinho",
        "category": "auto"
    },
    {
        "name": "Ferrugem",
        "category": "auto"
    },
    {
        "name": "Belo",
        "category": "auto"
    },
    {
        "name": "Péricles",
        "category": "auto"
    },
    {
        "name": "Bruno Cardoso",
        "category": "auto"
    },
    {
        "name": "Luiz Carlos",
        "category": "auto"
    },
    {
        "name": "Roberto Carlos",
        "category": "auto"
    },
    {
        "name": "Sandy",
        "category": "auto"
    },
    {
        "name": "Junior Lima",
        "category": "auto"
    },
    {
        "name": "Luan Santana",
        "category": "auto"
    },
    {
        "name": "Gusttavo Lima",
        "category": "auto"
    },
    {
        "name": "Jorge",
        "category": "auto"
    },
    {
        "name": "Mateus",
        "category": "auto"
    },
    {
        "name": "Henrique",
        "category": "auto"
    },
    {
        "name": "Juliano",
        "category": "auto"
    },
    {
        "name": "Zé Neto",
        "category": "auto"
    },
    {
        "name": "Cristiano",
        "category": "auto"
    },
    {
        "name": "Maiara",
        "category": "auto"
    },
    {
        "name": "Maraisa",
        "category": "auto"
    },
    {
        "name": "Simone Mendes",
        "category": "auto"
    },
    {
        "name": "Marília Mendonça",
        "category": "auto"
    },
    {
        "name": "Wesley Safadão",
        "category": "auto"
    },
    {
        "name": "Zé Felipe",
        "category": "auto"
    },
    {
        "name": "Ana Castela",
        "category": "auto"
    },
    {
        "name": "Liniker",
        "category": "auto"
    },
    {
        "name": "Tulipa Ruiz",
        "category": "auto"
    },
    {
        "name": "Céu",
        "category": "auto"
    },
    {
        "name": "Silva",
        "category": "auto"
    },
    {
        "name": "Pitty",
        "category": "auto"
    },
    {
        "name": "Lucas Silveira",
        "category": "auto"
    },
    {
        "name": "Di Ferrero",
        "category": "auto"
    },
    {
        "name": "Jão",
        "category": "auto"
    },
    {
        "name": "Vitão",
        "category": "auto"
    },
    {
        "name": "Rodrigo Melim",
        "category": "auto"
    },
    {
        "name": "Letícia Novaes",
        "category": "auto"
    },
    {
        "name": "Duda Beat",
        "category": "auto"
    },
    {
        "name": "Jade Baraldo",
        "category": "auto"
    },
    {
        "name": "Neymar Jr.",
        "category": "auto"
    },
    {
        "name": "Vinícius Júnior",
        "category": "auto"
    },
    {
        "name": "Rodrygo Goes",
        "category": "auto"
    },
    {
        "name": "Raphinha",
        "category": "auto"
    },
    {
        "name": "Gabriel Jesus",
        "category": "auto"
    },
    {
        "name": "Richarlison",
        "category": "auto"
    },
    {
        "name": "Gabigol",
        "category": "auto"
    },
    {
        "name": "Bruno Henrique",
        "category": "auto"
    },
    {
        "name": "Pedro",
        "category": "auto"
    },
    {
        "name": "Hulk",
        "category": "auto"
    },
    {
        "name": "Dudu",
        "category": "auto"
    },
    {
        "name": "Endrick",
        "category": "auto"
    },
    {
        "name": "Raphael Veiga",
        "category": "auto"
    },
    {
        "name": "Yuri Alberto",
        "category": "auto"
    },
    {
        "name": "Paulinho",
        "category": "auto"
    },
    {
        "name": "Alisson Becker",
        "category": "auto"
    },
    {
        "name": "Ederson",
        "category": "auto"
    },
    {
        "name": "Weverton",
        "category": "auto"
    },
    {
        "name": "Thiago Silva",
        "category": "auto"
    },
    {
        "name": "Marquinhos",
        "category": "auto"
    },
    {
        "name": "Casemiro",
        "category": "auto"
    },
    {
        "name": "Fred",
        "category": "auto"
    },
    {
        "name": "Philippe Coutinho",
        "category": "auto"
    },
    {
        "name": "Lucas Paquetá",
        "category": "auto"
    },
    {
        "name": "Antony",
        "category": "auto"
    },
    {
        "name": "Gabriel Martinelli",
        "category": "auto"
    },
    {
        "name": "Bruno Guimarães",
        "category": "auto"
    },
    {
        "name": "Everton Ribeiro",
        "category": "auto"
    },
    {
        "name": "Lucas Moura",
        "category": "auto"
    },
    {
        "name": "Alex",
        "category": "auto"
    },
    {
        "name": "Rogério Ceni",
        "category": "auto"
    },
    {
        "name": "Marcos",
        "category": "auto"
    },
    {
        "name": "Filipe Luís",
        "category": "auto"
    },
    {
        "name": "Daniel Alves",
        "category": "auto"
    },
    {
        "name": "Marcelo",
        "category": "auto"
    },
    {
        "name": "Maicon",
        "category": "auto"
    },
    {
        "name": "Miranda",
        "category": "auto"
    },
    {
        "name": "David Luiz",
        "category": "auto"
    },
    {
        "name": "Marta",
        "category": "auto"
    },
    {
        "name": "Formiga",
        "category": "auto"
    },
    {
        "name": "Cristiane",
        "category": "auto"
    },
    {
        "name": "Bia Zaneratto",
        "category": "auto"
    },
    {
        "name": "Debinha",
        "category": "auto"
    },
    {
        "name": "Tamires",
        "category": "auto"
    },
    {
        "name": "Ayrton Senna",
        "category": "auto"
    },
    {
        "name": "Rubens Barrichello",
        "category": "auto"
    },
    {
        "name": "Felipe Massa",
        "category": "auto"
    },
    {
        "name": "Nelson Piquet",
        "category": "auto"
    },
    {
        "name": "Guga Kuerten",
        "category": "auto"
    },
    {
        "name": "Bruno Soares",
        "category": "auto"
    },
    {
        "name": "Rebeca Andrade",
        "category": "auto"
    },
    {
        "name": "Daiane dos Santos",
        "category": "auto"
    },
    {
        "name": "Diego Hypólito",
        "category": "auto"
    },
    {
        "name": "Arthur Zanetti",
        "category": "auto"
    },
    {
        "name": "Rayssa Leal",
        "category": "auto"
    },
    {
        "name": "Letícia Bufoni",
        "category": "auto"
    },
    {
        "name": "Italo Ferreira",
        "category": "auto"
    },
    {
        "name": "Gabriel Medina",
        "category": "auto"
    },
    {
        "name": "Filipe Toledo",
        "category": "auto"
    },
    {
        "name": "Oscar Schmidt",
        "category": "auto"
    },
    {
        "name": "Tony Ramos",
        "category": "auto"
    },
    {
        "name": "Fernanda Montenegro",
        "category": "auto"
    },
    {
        "name": "Glória Pires",
        "category": "auto"
    },
    {
        "name": "Susana Vieira",
        "category": "auto"
    },
    {
        "name": "Lima Duarte",
        "category": "auto"
    },
    {
        "name": "Antônio Fagundes",
        "category": "auto"
    },
    {
        "name": "Lília Cabral",
        "category": "auto"
    },
    {
        "name": "Marieta Severo",
        "category": "auto"
    },
    {
        "name": "Patrícia Pillar",
        "category": "auto"
    },
    {
        "name": "Cláudia Raia",
        "category": "auto"
    },
    {
        "name": "Carolina Dieckmann",
        "category": "auto"
    },
    {
        "name": "Vera Fischer",
        "category": "auto"
    },
    {
        "name": "Deborah Secco",
        "category": "auto"
    },
    {
        "name": "Juliana Paes",
        "category": "auto"
    },
    {
        "name": "Grazi Massafera",
        "category": "auto"
    },
    {
        "name": "Paolla Oliveira",
        "category": "auto"
    },
    {
        "name": "Taís Araújo",
        "category": "auto"
    },
    {
        "name": "Camila Pitanga",
        "category": "auto"
    },
    {
        "name": "Débora Falabella",
        "category": "auto"
    },
    {
        "name": "Isabelle Drummond",
        "category": "auto"
    },
    {
        "name": "Adriana Esteves",
        "category": "auto"
    },
    {
        "name": "Giovanna Antonelli",
        "category": "auto"
    },
    {
        "name": "Giovanna Ewbank",
        "category": "auto"
    },
    {
        "name": "Nathalia Dill",
        "category": "auto"
    },
    {
        "name": "Marina Ruy Barbosa",
        "category": "auto"
    },
    {
        "name": "Sophie Charlotte",
        "category": "auto"
    },
    {
        "name": "Bruna Marquezine",
        "category": "auto"
    },
    {
        "name": "Larissa Manoela",
        "category": "auto"
    },
    {
        "name": "Maisa Silva",
        "category": "auto"
    },
    {
        "name": "Fábio Assunção",
        "category": "auto"
    },
    {
        "name": "Reynaldo Gianecchini",
        "category": "auto"
    },
    {
        "name": "Murilo Benício",
        "category": "auto"
    },
    {
        "name": "Cauã Reymond",
        "category": "auto"
    },
    {
        "name": "Wagner Moura",
        "category": "auto"
    },
    {
        "name": "Selton Mello",
        "category": "auto"
    },
    {
        "name": "Rodrigo Santoro",
        "category": "auto"
    },
    {
        "name": "Lázaro Ramos",
        "category": "auto"
    },
    {
        "name": "Mateus Solano",
        "category": "auto"
    },
    {
        "name": "Chay Suede",
        "category": "auto"
    },
    {
        "name": "Marcelo Serrado",
        "category": "auto"
    },
    {
        "name": "Dan Stulbach",
        "category": "auto"
    },
    {
        "name": "Rodrigo Lombardi",
        "category": "auto"
    },
    {
        "name": "Sophia Abrahão",
        "category": "auto"
    },
    {
        "name": "Paulo Gustavo",
        "category": "auto"
    },
    {
        "name": "Leandro Hassum",
        "category": "auto"
    },
    {
        "name": "Marcelo Adnet",
        "category": "auto"
    },
    {
        "name": "Tom Cavalcante",
        "category": "auto"
    },
    {
        "name": "Renato Aragão",
        "category": "auto"
    },
    {
        "name": "Dedé Santana",
        "category": "auto"
    },
    {
        "name": "Mussum",
        "category": "auto"
    },
    {
        "name": "Chico Anysio",
        "category": "auto"
    },
    {
        "name": "Tatá Werneck",
        "category": "auto"
    },
    {
        "name": "Fábio Porchat",
        "category": "auto"
    },
    {
        "name": "Dani Calabresa",
        "category": "auto"
    },
    {
        "name": "Rafinha Bastos",
        "category": "auto"
    },
    {
        "name": "Gregório Duvivier",
        "category": "auto"
    },
    {
        "name": "João Vicente de Castro",
        "category": "auto"
    },
    {
        "name": "Afonso Padilha",
        "category": "auto"
    },
    {
        "name": "Thiago Ventura",
        "category": "auto"
    },
    {
        "name": "Bruna Louise",
        "category": "auto"
    },
    {
        "name": "Igor Guimarães",
        "category": "auto"
    },
    {
        "name": "Murilo Couto",
        "category": "auto"
    },
    {
        "name": "Oscar Filho",
        "category": "auto"
    },
    {
        "name": "Ana Maria Braga",
        "category": "auto"
    },
    {
        "name": "Fátima Bernardes",
        "category": "auto"
    },
    {
        "name": "William Bonner",
        "category": "auto"
    },
    {
        "name": "Renata Vasconcellos",
        "category": "auto"
    },
    {
        "name": "Sandra Annenberg",
        "category": "auto"
    },
    {
        "name": "Maju Coutinho",
        "category": "auto"
    },
    {
        "name": "Poliana Abritta",
        "category": "auto"
    },
    {
        "name": "Evaristo Costa",
        "category": "auto"
    },
    {
        "name": "Pedro Bial",
        "category": "auto"
    },
    {
        "name": "Serginho Groisman",
        "category": "auto"
    },
    {
        "name": "Luciano Huck",
        "category": "auto"
    },
    {
        "name": "Angélica",
        "category": "auto"
    },
    {
        "name": "Eliana",
        "category": "auto"
    },
    {
        "name": "Silvio Santos",
        "category": "auto"
    },
    {
        "name": "Ratinho",
        "category": "auto"
    },
    {
        "name": "Danilo Gentili",
        "category": "auto"
    },
    {
        "name": "Marcos Mion",
        "category": "auto"
    },
    {
        "name": "Sabrina Sato",
        "category": "auto"
    },
    {
        "name": "Celso Portiolli",
        "category": "auto"
    },
    {
        "name": "Tiago Leifert",
        "category": "auto"
    },
    {
        "name": "Galvão Bueno",
        "category": "auto"
    },
    {
        "name": "Cléber Machado",
        "category": "auto"
    },
    {
        "name": "Caio Ribeiro",
        "category": "auto"
    },
    {
        "name": "Casimiro Miguel",
        "category": "auto"
    },
    {
        "name": "Neto",
        "category": "auto"
    },
    {
        "name": "Felipe Neto",
        "category": "auto"
    },
    {
        "name": "Luccas Neto",
        "category": "auto"
    },
    {
        "name": "Whindersson Nunes",
        "category": "auto"
    },
    {
        "name": "Kéfera Buchmann",
        "category": "auto"
    },
    {
        "name": "Christian Figueiredo",
        "category": "auto"
    },
    {
        "name": "Nah Cardoso",
        "category": "auto"
    },
    {
        "name": "Flavia Pavanelli",
        "category": "auto"
    },
    {
        "name": "Bianca Andrade",
        "category": "auto"
    },
    {
        "name": "Jade Picon",
        "category": "auto"
    },
    {
        "name": "Viih Tube",
        "category": "auto"
    },
    {
        "name": "GKay",
        "category": "auto"
    },
    {
        "name": "Carlinhos Maia",
        "category": "auto"
    },
    {
        "name": "Virgínia Fonseca",
        "category": "auto"
    },
    {
        "name": "Nilce Moretto",
        "category": "auto"
    },
    {
        "name": "Leon Martins",
        "category": "auto"
    },
    {
        "name": "Iberê Thenório",
        "category": "auto"
    },
    {
        "name": "Mari Fulfaro",
        "category": "auto"
    },
    {
        "name": "Felipe Castanhari",
        "category": "auto"
    },
    {
        "name": "T3ddy",
        "category": "auto"
    },
    {
        "name": "AuthenticGames",
        "category": "auto"
    },
    {
        "name": "Rezendeevil",
        "category": "auto"
    },
    {
        "name": "Enaldinho",
        "category": "auto"
    },
    {
        "name": "Renato Garcia",
        "category": "auto"
    },
    {
        "name": "Robin Hood Gamer",
        "category": "auto"
    },
    {
        "name": "Gato Galáctico",
        "category": "auto"
    },
    {
        "name": "Júlio Cocielo",
        "category": "auto"
    },
    {
        "name": "Juliana Baltar",
        "category": "auto"
    },
    {
        "name": "Planeta das Gêmeas",
        "category": "auto"
    },
    {
        "name": "Camila Loures",
        "category": "auto"
    },
    {
        "name": "Lucas Rangel",
        "category": "auto"
    },
    {
        "name": "Matheus Yurley",
        "category": "auto"
    },
    {
        "name": "Everson Zoio",
        "category": "auto"
    },
    {
        "name": "LubaTV",
        "category": "auto"
    },
    {
        "name": "Cellbit",
        "category": "auto"
    },
    {
        "name": "Alanzoka",
        "category": "auto"
    },
    {
        "name": "Gaules",
        "category": "auto"
    },
    {
        "name": "Nobru",
        "category": "auto"
    },
    {
        "name": "Cerol",
        "category": "auto"
    },
    {
        "name": "PlayHard",
        "category": "auto"
    },
    {
        "name": "Piuzinho",
        "category": "auto"
    },
    {
        "name": "Patife",
        "category": "auto"
    },
    {
        "name": "FalleN",
        "category": "auto"
    },
    {
        "name": "Coldzera",
        "category": "auto"
    },
    {
        "name": "fer",
        "category": "auto"
    },
    {
        "name": "TACO",
        "category": "auto"
    },
    {
        "name": "brTT",
        "category": "auto"
    },
    {
        "name": "Yoda",
        "category": "auto"
    },
    {
        "name": "Kami",
        "category": "auto"
    },
    {
        "name": "BAK",
        "category": "auto"
    },
    {
        "name": "Loud Coringa",
        "category": "auto"
    },
    {
        "name": "Fred Bruno",
        "category": "auto"
    },
    {
        "name": "Bolívia Zica",
        "category": "auto"
    },
    {
        "name": "Igor 3K",
        "category": "auto"
    },
    {
        "name": "Monark",
        "category": "auto"
    },
    {
        "name": "Arthur Petry",
        "category": "auto"
    },
    {
        "name": "Igão",
        "category": "auto"
    },
    {
        "name": "Mítico",
        "category": "auto"
    },
    {
        "name": "Rafa Kalimann",
        "category": "auto"
    },
    {
        "name": "Juliette Freire",
        "category": "auto"
    },
    {
        "name": "Thelminha",
        "category": "auto"
    },
    {
        "name": "Gil do Vigor",
        "category": "auto"
    },
    {
        "name": "Pocah",
        "category": "auto"
    },
    {
        "name": "Deolane Bezerra",
        "category": "auto"
    },
    {
        "name": "MC Loma",
        "category": "auto"
    },
    {
        "name": "Tirullipa",
        "category": "auto"
    },
    {
        "name": "Maria Clara",
        "category": "auto"
    },
    {
        "name": "Nath Arcuri",
        "category": "auto"
    },
    {
        "name": "Primo Rico",
        "category": "auto"
    },
    {
        "name": "Raul Sena",
        "category": "auto"
    },
    {
        "name": "Niina Secrets",
        "category": "auto"
    },
    {
        "name": "Karen Bachini",
        "category": "auto"
    },
    {
        "name": "Mari Maria",
        "category": "auto"
    },
    {
        "name": "Camila Coelho",
        "category": "auto"
    }
]